quart_cors/__init__.py
quart_cors/py.typed
Quart_CORS-0.5.0.dist-info/LICENSE
Quart_CORS-0.5.0.dist-info/METADATA
Quart_CORS-0.5.0.dist-info/WHEEL
Quart_CORS-0.5.0.dist-info/top_level.txt
Quart_CORS-0.5.0.dist-info/RECORD
